certbot_dns_dynu/__init__.py
certbot_dns_dynu/dns_dynu.py
certbot_dns_dynu/dns_dynu_test.py
certbot_dns_dynu-0.0.4.dist-info/LICENSE
certbot_dns_dynu-0.0.4.dist-info/METADATA
certbot_dns_dynu-0.0.4.dist-info/WHEEL
certbot_dns_dynu-0.0.4.dist-info/entry_points.txt
certbot_dns_dynu-0.0.4.dist-info/top_level.txt
certbot_dns_dynu-0.0.4.dist-info/RECORD
